<?xml version="1.0"?>
<faces-config version="2.0" xmlns="http://java.sun.com/xml/ns/javaee"
 xmlns:xi="http://www.w3.org/2001/XInclude"
 xmlns:xsi="http://www.w3.org/2001/XMLSchema-instance" xsi:schemaLocation="http://java.sun.com/xml/ns/javaee     http://java.sun.com/xml/ns/javaee/web-facesconfig_2_0.xsd">
 <navigation-rule>
  <from-view-id>/dronesAdmin.xhtml</from-view-id>
  <navigation-case>
   <from-outcome>initSuccess</from-outcome>
   <to-view-id>/undrone.xhtml</to-view-id>
  </navigation-case>
 </navigation-rule>
 <navigation-rule>
  <from-view-id>/drones.xhtml</from-view-id>
  <navigation-case>
   <from-outcome>initSuccess</from-outcome>
   <to-view-id>/undrone.xhtml</to-view-id>
  </navigation-case>
 </navigation-rule>
 <navigation-rule>
  <from-view-id>/abonnements.xhtml</from-view-id>
  <navigation-case>
   <from-outcome>analogic</from-outcome>
   <to-view-id>/analogicData.xhtml</to-view-id>
  </navigation-case>
 </navigation-rule>
<navigation-rule>
  <from-view-id>/abonnements.xhtml</from-view-id>
  <navigation-case>
   <from-outcome>numeric</from-outcome>
   <to-view-id>/numericData.xhtml</to-view-id>
  </navigation-case>
 </navigation-rule>
<navigation-rule>
  <from-view-id>/abonnements.xhtml</from-view-id>
  <navigation-case>
   <from-outcome>sensor</from-outcome>
   <to-view-id>/dashboard.xhtml</to-view-id>
  </navigation-case>
 </navigation-rule>
 <navigation-rule>
  <from-view-id>/undrone.xhtml</from-view-id>
  <navigation-case>
   <from-outcome>analogic</from-outcome>
   <to-view-id>/analogicData.xhtml</to-view-id>
  </navigation-case>
 </navigation-rule>
<navigation-rule>
  <from-view-id>/undrone.xhtml</from-view-id>
  <navigation-case>
   <from-outcome>numeric</from-outcome>
   <to-view-id>/numericData.xhtml</to-view-id>
  </navigation-case>
 </navigation-rule>
<navigation-rule>
  <from-view-id>/undrone.xhtml</from-view-id>
  <navigation-case>
   <from-outcome>sensor</from-outcome>
   <to-view-id>/dashboard.xhtml</to-view-id>
  </navigation-case>
 </navigation-rule>
</faces-config>

